{
  "date": "2026-06-08",
  "count": 11,
  "items": [
    {
      "rank": 1,
      "title": "The Cypherpunk Library",
      "url": "https://www.cypherpunkbooks.com",
      "desc": "A personal collection of good public-domain reads. Free to read, free to keep.",
      "tag": "综合",
      "sources": [
        "hackernews"
      ],
      "score": 50.0
    },
    {
      "rank": 2,
      "title": "Dopamine Fracking",
      "url": "https://igerman.cc/blog/dopamine-fracking",
      "desc": "The act of pumping immense, disproportionate resources into a previously casual or complex and layered activity to forcefully extract and squeeze out the purest, most concentrated dopamine hit",
      "tag": "综合",
      "sources": [
        "hackernews"
      ],
      "score": 50.0
    },
    {
      "rank": 3,
      "title": "1k Data Breaches Later, the Disclosure Lag Is Worse",
      "url": "https://www.troyhunt.com/1000-data-breaches-later-the-disclosure-lag-is-worse-than-ever",
      "desc": "Today, I loaded the 1,000th data breach into Have I Been Pwned. Reflecting on that milestone number, I pondered how to mark the occasion in writing, and what immediately came to mind was a very simple",
      "tag": "综合",
      "sources": [
        "hackernews"
      ],
      "score": 50.0
    },
    {
      "rank": 4,
      "title": "Building from zero after addiction, prison, and a felony",
      "url": "https://gavinray97.github.io/blog/building-from-zero-after-addiction-prison-felony",
      "desc": "I spent ages 14-16 in a maximum-security juvenile prison, became a felon at 19, lost almost everything to addiction, and later rebuilt my life through software, open source, and a few people who took ",
      "tag": "综合",
      "sources": [
        "hackernews"
      ],
      "score": 50.0
    },
    {
      "rank": 5,
      "title": "APC–2 – A professional record cutter for producing original playback discs",
      "url": "https://teenage.engineering/products/apc-2",
      "desc": "aÂ professional record cutter built and designed for producingoriginal playbackÂ discs with superior sound quality in realÂ time.Â",
      "tag": "综合",
      "sources": [
        "hackernews"
      ],
      "score": 50.0
    },
    {
      "rank": 6,
      "title": "To my students",
      "url": "http://ozark.hendrix.edu/~yorgey/forest/00fd/index.xml",
      "desc": "",
      "tag": "综合",
      "sources": [
        "lobsters"
      ],
      "score": 47.0
    },
    {
      "rank": 7,
      "title": "Premature Optimization is Fun Sometimes",
      "url": "https://invlpg.com/posts/2025-06-19-premature-optimization.html",
      "desc": "",
      "tag": "综合",
      "sources": [
        "lobsters"
      ],
      "score": 47.0
    },
    {
      "rank": 8,
      "title": "In Defense of YAML",
      "url": "https://opensource.posit.co/blog/2026-05-21_in-defense-of-yaml",
      "desc": "",
      "tag": "综合",
      "sources": [
        "lobsters"
      ],
      "score": 47.0
    },
    {
      "rank": 9,
      "title": "April in Servo: new Android UI, focus, forms, security fixes, and more",
      "url": "https://servo.org/blog/2026/05/31/april-in-servo",
      "desc": "",
      "tag": "安全",
      "sources": [
        "lobsters"
      ],
      "score": 47.0
    },
    {
      "rank": 10,
      "title": "GentleOS - A pair of hobby OSes for vintage 32-bit and 16-bit PCs",
      "url": "https://github.com/luke8086/gentleos32",
      "desc": "",
      "tag": "AI/ML",
      "sources": [
        "lobsters"
      ],
      "score": 47.0
    },
    {
      "rank": 11,
      "title": "蚂蚁国际推出移动智能体协议AMP，海外AI支付迈向统一标准",
      "url": "https://www.infoq.cn/article/gsr7ftxv2trgqjsimkmp",
      "desc": "",
      "tag": "AI/ML",
      "sources": [
        "infoq_cn"
      ],
      "score": 45.5
    }
  ]
}